{
  "main": {
    "id": "0f40fbf571f8d505",
    "type": "split",
    "children": [
      {
        "id": "0796ddb22585e79f",
        "type": "tabs",
        "children": [
          {
            "id": "d00085b673c0d565",
            "type": "leaf",
            "state": {
              "type": "markdown",
              "state": {
                "file": "Topics/topic_romi_modeling.md",
                "mode": "source",
                "source": false
              },
              "icon": "lucide-file",
              "title": "topic_romi_modeling"
            }
          }
        ]
      }
    ],
    "direction": "vertical"
  },
  "left": {
    "id": "c683c51744652c64",
    "type": "split",
    "children": [
      {
        "id": "18d0e72e3c447e89",
        "type": "tabs",
        "children": [
          {
            "id": "5ced17afc5e0d088",
            "type": "leaf",
            "state": {
              "type": "file-explorer",
              "state": {
                "sortOrder": "alphabetical",
                "autoReveal": false
              },
              "icon": "lucide-folder-closed",
              "title": "Files"
            }
          },
          {
            "id": "b80fe5140bc4c1c3",
            "type": "leaf",
            "state": {
              "type": "search",
              "state": {
                "query": "tag:#State",
                "matchingCase": false,
                "explainSearch": false,
                "collapseAll": false,
                "extraContext": false,
                "sortOrder": "alphabetical"
              },
              "icon": "lucide-search",
              "title": "Search"
            }
          },
          {
            "id": "001e141b55298925",
            "type": "leaf",
            "state": {
              "type": "bookmarks",
              "state": {},
              "icon": "lucide-bookmark",
              "title": "Bookmarks"
            }
          }
        ]
      }
    ],
    "direction": "horizontal",
    "width": 449.5
  },
  "right": {
    "id": "43db80c1abec9147",
    "type": "split",
    "children": [
      {
        "id": "79c210f87094f2ba",
        "type": "tabs",
        "children": [
          {
            "id": "7c350ba4d0b98591",
            "type": "leaf",
            "state": {
              "type": "backlink",
              "state": {
                "file": "Insights/observer.md",
                "collapseAll": false,
                "extraContext": false,
                "sortOrder": "alphabetical",
                "showSearch": false,
                "searchQuery": "",
                "backlinkCollapsed": false,
                "unlinkedCollapsed": true
              },
              "icon": "links-coming-in",
              "title": "Backlinks for observer"
            }
          },
          {
            "id": "4efebc2fe669a646",
            "type": "leaf",
            "state": {
              "type": "outgoing-link",
              "state": {
                "file": "Insights/observer.md",
                "linksCollapsed": false,
                "unlinkedCollapsed": true
              },
              "icon": "links-going-out",
              "title": "Outgoing links from observer"
            }
          },
          {
            "id": "9b50898d1fb992f0",
            "type": "leaf",
            "state": {
              "type": "tag",
              "state": {
                "sortOrder": "frequency",
                "useHierarchy": true,
                "showSearch": false,
                "searchQuery": ""
              },
              "icon": "lucide-tags",
              "title": "Tags"
            }
          },
          {
            "id": "1100bb22b5ec3cc0",
            "type": "leaf",
            "state": {
              "type": "all-properties",
              "state": {
                "sortOrder": "frequency",
                "showSearch": false,
                "searchQuery": ""
              },
              "icon": "lucide-archive",
              "title": "All properties"
            }
          },
          {
            "id": "149390dd64434efe",
            "type": "leaf",
            "state": {
              "type": "outline",
              "state": {
                "file": "Insights/observer.md",
                "followCursor": false,
                "showSearch": false,
                "searchQuery": ""
              },
              "icon": "lucide-list",
              "title": "Outline of observer"
            }
          }
        ]
      }
    ],
    "direction": "horizontal",
    "width": 300,
    "collapsed": true
  },
  "left-ribbon": {
    "hiddenItems": {
      "switcher:Open quick switcher": false,
      "graph:Open graph view": false,
      "canvas:Create new canvas": false,
      "daily-notes:Open today's daily note": false,
      "templates:Insert template": false,
      "command-palette:Open command palette": false,
      "bases:Create new base": false,
      "webpage-html-export:Export as HTML": false
    }
  },
  "active": "d00085b673c0d565",
  "lastOpenFiles": [
    "Topics/topic_review_of_signed_numbers.md",
    "Topics/topic_romi_modeling.md",
    "Topics/topic_virtual_com_ports.md",
    "Case Studies/case_romi_observer.md",
    "References/reference_state_feedback.md",
    "Topics/topic_intro_to_state_feedback.md",
    "Case Studies/case_motor_observer.md",
    "Topics/topic_scheduling_tasks.md",
    "Topics/topic_serial_communication.md",
    "Topics/topic_fsms_and_state_transition_diagrams.md",
    "Topics/topic_task_diagrams.md",
    "Topics/topic_priority_schedulers.md",
    "Topics/topic_i2c_communication.md",
    "Topics/topic_inertial_measurement_units.md",
    "Topics/topic_file_io.md",
    "index.md",
    "Topics/topic_software_timing.md",
    "Topics/topic_philosophy_of_mechatronics.md",
    "Topics/topic_python_fundamentals.md",
    "Topics/topic_intro_to_feedback_and_controls.md",
    "Topics/topic_intro_to_generators.md",
    "Topics/topic_gpio.md",
    "Topics/topic_hardware_overview.md",
    "Topics/topic_collections.md",
    "Topics/topic_coop_user_io.md",
    "Topics/topic_crystals_timers_and_counters.md",
    "Images/romi_isometric_view.svg",
    "Images/romi_isometric.svg",
    "Images/romi_isometric_view_Artboard 1-01.svg",
    "Images/romi_isometric_view.jpeg",
    "Images/romi_isometric_view.png",
    "Images/shoe_coms.svg",
    "figures",
    "Cooperative Character I",
    "Topics",
    "Images/example_3rd_order_poles_discrete.svg",
    "Images/example_3rd_order_poles_continuous.svg",
    "Images/trapezoidal_method.svg",
    "Images/backward_difference.svg",
    "Case Studies",
    "Images/Unconfirmed 378910.crdownload",
    "New folder",
    "Untitled"
  ]
}